textual_wifi/__init__.py
textual_wifi/__main__.py
textual_wifi/app_header.py
textual_wifi/app_loading_indicator.py
textual_wifi/app_password_input.py
textual_wifi/app_search.py
textual_wifi/app_table.py
textual_wifi/main.py
textual_wifi/textual_wifi.css
textual_wifi/textual_wifi.py
textual_wifi/utils.py
textual_wifi-0.4.0.dist-info/entry_points.txt
textual_wifi-0.4.0.dist-info/WHEEL
textual_wifi-0.4.0.dist-info/METADATA
textual_wifi-0.4.0.dist-info/RECORD
