Metadata-Version: 2.1
Name: textual-wifi
Version: 0.4.0
Summary: A wifi application build with textual and nmcli (py)
License: MIT
Author: Dmitrij Vinokour
Author-email: vinokour.dmitrij@gmail.com
Requires-Python: >=3.7,<4.0
Classifier: License :: OSI Approved :: MIT License
Classifier: Programming Language :: Python :: 3
Classifier: Programming Language :: Python :: 3.7
Classifier: Programming Language :: Python :: 3.8
Classifier: Programming Language :: Python :: 3.9
Classifier: Programming Language :: Python :: 3.10
Classifier: Programming Language :: Python :: 3.11
Requires-Dist: nmcli (>=1.1.2,<2.0.0)
Requires-Dist: textual[dev] (>=0.16.0,<0.17.0)
